vcdip.py
vcdip-0.0.2.dist-info/LICENSE
vcdip-0.0.2.dist-info/METADATA
vcdip-0.0.2.dist-info/WHEEL
vcdip-0.0.2.dist-info/top_level.txt
vcdip-0.0.2.dist-info/RECORD
