Metadata-Version: 2.1
Name: vcdip
Version: 0.0.2
Summary: Digital image processing
Author: aiml department
Author-email: aiml5thsem@gmail.com
License: MIT
Keywords: Digital image processing lab,diplab
Classifier: Programming Language :: Python :: 3
Classifier: License :: OSI Approved :: MIT License
Classifier: Operating System :: OS Independent
Requires-Python: >=3.7
License-File: LICENSE
Requires-Dist: sb6
